aiodiskqueue/__init__.py
aiodiskqueue/exceptions.py
aiodiskqueue/queues.py
aiodiskqueue/utils.py
aiodiskqueue/engines/__init__.py
aiodiskqueue/engines/base.py
aiodiskqueue/engines/dbm.py
aiodiskqueue/engines/simple.py
aiodiskqueue/engines/sqlite.py
aiodiskqueue-0.1.2.dist-info/LICENSE
aiodiskqueue-0.1.2.dist-info/WHEEL
aiodiskqueue-0.1.2.dist-info/METADATA
aiodiskqueue-0.1.2.dist-info/RECORD
