Metadata-Version: 2.1
Name: aiodiskqueue
Version: 0.1.2
Summary: Persistent queue for Python AsyncIO.
Author-email: Erik Kalkoken <kalkoken87@gmail.com>
Requires-Python: >=3.8
Classifier: Intended Audience :: Developers
Classifier: License :: OSI Approved :: MIT License
Classifier: Programming Language :: Python
Classifier: Programming Language :: Python :: 3.8
Classifier: Programming Language :: Python :: 3.9
Classifier: Programming Language :: Python :: 3.10
Classifier: Programming Language :: Python :: 3.11
Requires-Dist: aiodbm>=0.4.0
Requires-Dist: aiofiles>=23.1.0 ; extra == "aiofiles"
Requires-Dist: aiosqlite>=0.19.0 ; extra == "aiosqlite"
Project-URL: Documentation, https://aiodiskqueue.readthedocs.io/en/latest/
Project-URL: Source, https://github.com/ErikKalkoken/aiodiskqueue
Project-URL: Tracker, https://github.com/ErikKalkoken/aiodiskqueue/issues
Provides-Extra: aiofiles
Provides-Extra: aiosqlite
